universal_common/__init__.py
universal_common-1.2.0.dist-info/METADATA
universal_common-1.2.0.dist-info/WHEEL
universal_common-1.2.0.dist-info/licenses/LICENSE
universal_common-1.2.0.dist-info/RECORD
