Metadata-Version: 2.3
Name: universal_common
Version: 1.2.0
Summary: Library that extends the Python base class library with utility functions.
Author-email: Andrew Ong <ong.andrew@gmail.com>
License-File: LICENSE
Classifier: Development Status :: 5 - Production/Stable
Classifier: License :: CC0 1.0 Universal (CC0 1.0) Public Domain Dedication
Classifier: Operating System :: OS Independent
Classifier: Programming Language :: Python :: 3
Requires-Python: >=3.9
